browserjquery/__init__.py
browserjquery/data/jquery.js
browserjquery/jquery.py
browserjquery/jquery_scripts.py
browserjquery/log_config/log_config.yaml
browserjquery/settings.py
browserjquery-2.0.1.dist-info/LICENSE
browserjquery-2.0.1.dist-info/METADATA
browserjquery-2.0.1.dist-info/WHEEL
browserjquery-2.0.1.dist-info/RECORD
