Metadata-Version: 2.1
Name: browserjquery
Version: 2.0.1
Summary: A Python library for using jQuery with Selenium WebDriver
Home-page: https://github.com/inquilabee/BrowserJQuery
License: MIT
Keywords: selenium,selenium python,browserjquery,browser automation,python jquery
Author: Vishal Kumar Mishra
Author-email: vishal.k.mishra2@gmail.com
Requires-Python: >=3.13,<4.0
Classifier: License :: OSI Approved :: MIT License
Classifier: Programming Language :: Python :: 3
Classifier: Programming Language :: Python :: 3.13
Requires-Dist: django-environ (>=0.11.2,<0.12.0)
Requires-Dist: python-dotenv (>=1.0.0,<2.0.0)
Requires-Dist: pyyaml (>=6.0.1,<7.0.0)
Requires-Dist: ruff (>=0.11.13,<0.12.0)
Requires-Dist: selenium (>=4.12.0,<5.0.0)
Project-URL: Repository, https://github.com/inquilabee/BrowserJQuery
